melonipc/__init__.py
melonipc/client.py
melonipc/exceptions.py
melonipc/packet.py
melonipc/server.py
melonipc-0.1.0.dist-info/METADATA
melonipc-0.1.0.dist-info/WHEEL
melonipc-0.1.0.dist-info/RECORD
