Metadata-Version: 2.1
Name: melonipc
Version: 0.1.0
Summary: IPC for melon-discordbot
Author: inthedark.org
Requires-Python: >=3.10,<4.0
Classifier: Programming Language :: Python :: 3
Classifier: Programming Language :: Python :: 3.10
Classifier: Programming Language :: Python :: 3.11
Requires-Dist: starlette (>=0.31,<0.32)
Requires-Dist: websockets (>=10.4,<11.0)
